bagit_utils/__init__.py
bagit_utils/bagit.py
bagit_utils/cli.py
bagit_utils/common.py
bagit_utils/validator.py
bagit_utils-1.2.4.dist-info/licenses/LICENSE
bagit_utils-1.2.4.dist-info/METADATA
bagit_utils-1.2.4.dist-info/WHEEL
bagit_utils-1.2.4.dist-info/entry_points.txt
bagit_utils-1.2.4.dist-info/top_level.txt
bagit_utils-1.2.4.dist-info/RECORD
