Metadata-Version: 2.4
Name: bagit-utils
Version: 1.2.4
Summary: python library and command line interface for creating and interacting with files in the BagIt-format
Home-page: https://pypi.org/project/bagit-utils/
Author: Steffen Richters-Finger
Author-email: srichters@uni-muenster.de
License: MIT
Project-URL: Source, https://github.com/RichtersFinger/bagit-utils
Classifier: Development Status :: 5 - Production/Stable
Classifier: Intended Audience :: Developers
Classifier: Topic :: Software Development :: Libraries
Classifier: Topic :: Communications :: File Sharing
Classifier: License :: OSI Approved :: MIT License
Classifier: Programming Language :: Python :: 3
Classifier: Programming Language :: Python :: 3.10
Classifier: Programming Language :: Python :: 3.11
Classifier: Programming Language :: Python :: 3.12
Requires-Python: >=3.10
License-File: LICENSE
Provides-Extra: cli
Requires-Dist: befehl<1.0.0,>=0.1.2; extra == "cli"
Dynamic: author
Dynamic: author-email
Dynamic: classifier
Dynamic: description
Dynamic: description-content-type
Dynamic: home-page
Dynamic: license
Dynamic: license-file
Dynamic: project-url
Dynamic: provides-extra
Dynamic: requires-python
Dynamic: summary
